CHANGES.txt
LICENSE.txt
MANIFEST.in
README.rst
setup.py
filedict/__init__.py
filedict/__main__.py
filedict/base_sharded_storage.py
filedict/base_storage.py
filedict/file_counter.py
filedict/storage_file.py
filedict/version.py
filedict.egg-info/PKG-INFO
filedict.egg-info/SOURCES.txt
filedict.egg-info/dependency_links.txt
filedict.egg-info/not-zip-safe
filedict.egg-info/requires.txt
filedict.egg-info/top_level.txt
filedict/test/__init__.py
filedict/test/__main__.py
filedict/test/test_sharded.py
filedict/test/test_smoke.py