Metadata-Version: 1.1
Name: filedict
Version: 0.0.6
Summary: Fast & simple key-value storage.
Home-page: https://bitbucket.org/dkuryakin/filedict
Author: David Kuryakin
Author-email: dkuryakin@gmail.com
License: unlicense
Download-URL: https://bitbucket.org/dkuryakin/filedict/get/master.tar.gz
Keywords: storage,hash table,key value,database
Platform: any
Classifier: Development Status :: 3 - Alpha
Classifier: Environment :: Other Environment
Classifier: Intended Audience :: Developers
Classifier: License :: Freeware
Classifier: Operating System :: OS Independent
Classifier: Programming Language :: Python
Classifier: Topic :: Database :: Database Engines/Servers
